vomit/__init__.py
vomit-0.2.dist-info/METADATA
vomit-0.2.dist-info/WHEEL
vomit-0.2.dist-info/top_level.txt
vomit-0.2.dist-info/RECORD
