Metadata-Version: 2.1
Name: vomit
Version: 0.2
Summary: The new pop()
Home-page: https://github.com/MiTo0o
Author: MiTo
Author-email: derzanchiang1800@gmail.com
License: MIT
Platform: UNKNOWN
